{
  "IsEncrypted": false,
  "Values": {
    "AzureWebJobsStorage": "[Add your connection string here]",
    "StorageConnectionString": "[Add your connection string here]",
    "EventHubConnectionString": "[Add your connection string here]",
    "IoTHubConnectionString": "[Add your connection string here]",
    "SQLConnectionString": "[Add your connection string here]",
    "BackfillMethodName": "BackfillMethod",
    "DetectionEventHubName": "detected-data-gaps",
    "ExecutionEventHubName": "backfill-requests",
    "IoTDeviceId": "",
    "IoTMethodId": "ReliableRelayModule",
    "StorageQueueName": "data-gap-backfill-requests",
    "DirectMethodResponseTimeoutSeconds": "10",
    "BackfillTimeout": "10800",
    "DataGapsTTLSeconds": "86400",
    "DetectionRetryInvincibleSeconds": "3600",
    "InitialDetectionInvincibleSeconds": "1",
    "FUNCTIONS_WORKER_RUNTIME": "dotnet"
  }
}
